z3slif1_lite/__init__.py
z3slif1_lite/z3slif1_lite.pyd
z3slif1_lite/z3slif1_lite.pyi
z3slif1_lite-0.2.0.data/data/tests/test_zcube_api.py
z3slif1_lite-0.2.0.dist-info/licenses/LICENSE
z3slif1_lite-0.2.0.dist-info/METADATA
z3slif1_lite-0.2.0.dist-info/WHEEL
z3slif1_lite-0.2.0.dist-info/top_level.txt
z3slif1_lite-0.2.0.dist-info/RECORD
