Metadata-Version: 2.4
Name: z3slif1-lite
Version: 0.2.0
Summary: Lite version of zCube Developer Kit for SLI-F1 device (non-commercial use only)
Home-page: https://www.eksimracing.org/zcube-developer-kit
Author: Zappadoc
Author-email: support@eksimracing.org
License: CC BY-NC 4.0
Project-URL: Homepage, https://www.eksimracing.org/zcube-developer-kit/
Project-URL: Documentation, https://zappadoc.com/dev-support/zcube-developer-kit-for-python/
Project-URL: License, https://creativecommons.org/licenses/by-nc/4.0/
Keywords: zcube z3slif1 lite non-commercial developer kit
Classifier: Development Status :: 5 - Production/Stable
Classifier: Operating System :: Microsoft :: Windows
Classifier: Topic :: Software Development :: Libraries
Classifier: Topic :: Education
Classifier: Topic :: Games/Entertainment
Classifier: Topic :: Scientific/Engineering
Classifier: Intended Audience :: Developers
Classifier: Intended Audience :: Science/Research
Classifier: Intended Audience :: End Users/Desktop
Classifier: License :: Free for non-commercial use
Classifier: Programming Language :: Python :: 3 :: Only
Classifier: Programming Language :: Python :: 3.6
Classifier: Programming Language :: Python :: 3.8
Classifier: Programming Language :: Python :: 3.9
Classifier: Programming Language :: Python :: 3.10
Classifier: Programming Language :: Python :: 3.11
Classifier: Programming Language :: Python :: 3.12
Requires-Python: >=3.6
License-File: LICENSE
Dynamic: author
Dynamic: author-email
Dynamic: classifier
Dynamic: description
Dynamic: description-content-type
Dynamic: home-page
Dynamic: keywords
Dynamic: license
Dynamic: license-file
Dynamic: project-url
Dynamic: requires-python
Dynamic: summary
